{
  "name": "Garrett Morales",
  "age": 20,
  "address": {
    "street": "Coag Pass",
    "city": "Ristifjil",
    "state": "WA",
    "zip": "25787"
  },
  "contact": {
    "phone": "(541) 998-7975",
    "servicePhone": "800162624"
  },
  "birthday": "1997-11-12T02:02:01.704Z",
  "ip": "251.61.28.207",
  "foo": "bar",
  "profile": {
    "about": "He ijcohu goovalem igi omve huj dip tavjef dafuhvir tipejcan uvova uto. Gabjerivo fuco zovemuja ovu legpa ih taf ni hozpo led worug itbunin hiz epaduvma zuhkevri michoti nobo vevvovuz. Pa zorac lot co nati cuhgun dutlef nej vumog dic gufo bobedo josuif lagarziz kifito. Bodor ebazosdu ewlufa ogvew uftec buftegdag pi are sahatbo niragsed kifobpez ze seoze di okmohji fu dak fepiz. Uliku eh hib ruvlokeh hotu wiw azova joanra ut cakgoil pone kejuz munaza cim nanoke go cisfesbe.",
    "bio": "Ombahtit egesibe gejepegaf faddob buhe jubmuzsus hipodi gefnobi raediz ka enwagef up merivegov alzov huji. Mi uboaw melfopole ejiuboiv ku roca busat cup negbak mad bumov favatzuf gugtuvto sokil cag ogu pal piseiru. Ezuwujok zawoge sivus fodo bof pa namam fesbe vimeh epi vud rinip apufobo ig jakehhe gulo jabina ujsotoc. Zod gaszerwe er wugiz kat bos zo toikebow to seogo juhru sejakuc muuheat. Vehiv voeru ejoonewu tatkapo vadavri robcug zigcu wan bej jafante zus bedeleka in gaj ababulut sudo. Sateroj fij midki kif tub bes ne ma ji as aveepom kuges kijeico rencaah. Okdutre uwla nekperna abta no bi oro pod hihkuve timaema dohbufha tul gavibe kikfenfuz tajuzoga."
  },
  "apiKey": "461917030605d841cd9311ec7b013cfd3445676e157e8f7117efa90079f834fc",
  "currency": {
    "code": "KRW",
    "name": "Korea (South) Won"
  }
}