{
  "name": "Loretta Salazar",
  "age": 47,
  "address": {
    "street": "Kidi Road",
    "city": "Gupwuhij",
    "state": "MI",
    "zip": "98934"
  },
  "contact": {
    "phone": "(369) 698-2764",
    "servicePhone": "800622116"
  },
  "birthday": "1997-09-28T07:58:33.916Z",
  "ip": "42.74.43.80",
  "foo": "bar",
  "profile": {
    "about": "Itgah fagoten lolivzev ic ujwa tewmelduh id gew gafo ol atpez saz bet. Udpatlow wo bep okihib ala umehubiw si medtobwi futwalpu pelul mawutkel lajpiwiw nicudami. Wo feke teenma obo ijigocof ru laewu ohekig sufcioti maeza ne losesuso kowewem bupma dalberub ki.",
    "bio": "Atibiwme rabbonov lek uz docpewhac ute iwijunzu arudog kakzeb lit naemno jisij ihoworuh. Lad wanum jijmeg vapziele maj sudot ufeze wawik ka buevice gomkimit pu jiplen li zuafji ofbaup nawnib. Hivnoca suh lopoko sasgowof til jomji ovupa lippep coj eg udiloz cuc bizij efcew. Muled gonigog ka latase zugugo avu po mul emfan je azgozmif zeaniog cerig. Gizumed peg pusme pisaza woku varina tu lekujni apiwaw huwo giwrinhep metlame puelaba bepokek ji utzulsu fub zibkolsu."
  },
  "apiKey": "7a5e5b2ce80cb1304d13a60f009fffee84a89e701daa239dc0e1b0cceca5909e",
  "currency": {
    "code": "NAD",
    "name": "Namibia Dollar"
  }
}